{
  "timestamp": "2026-02-01T22:22:14.418730",
  "period": "5d",
  "series": [
    {
      "name": "Technology",
      "data": [
        {
          "x": "NVDA",
          "y": 34200210571.0,
          "price": 191.13,
          "change": -0.72,
          "color": "#EF9A9A"
        },
        {
          "x": "MSFT",
          "y": 25159228916.0,
          "price": 430.29,
          "change": -0.74,
          "color": "#EF9A9A"
        },
        {
          "x": "AAPL",
          "y": 23963653663.0,
          "price": 259.48,
          "change": 0.46,
          "color": "#81C784"
        },
        {
          "x": "AMD",
          "y": 9456132333.0,
          "price": 236.73,
          "change": -6.13,
          "color": "#B71C1C"
        },
        {
          "x": "AVGO",
          "y": 9371780925.0,
          "price": 331.3,
          "change": 0.17,
          "color": "#81C784"
        },
        {
          "x": "ORCL",
          "y": 4482303434.0,
          "price": 164.58,
          "change": -2.62,
          "color": "#F44336"
        },
        {
          "x": "CRM",
          "y": 2353170889.0,
          "price": 212.29,
          "change": -0.84,
          "color": "#EF9A9A"
        },
        {
          "x": "ADBE",
          "y": 1674838725.0,
          "price": 293.25,
          "change": 0.55,
          "color": "#81C784"
        }
      ]
    },
    {
      "name": "Consumer Disc.",
      "data": [
        {
          "x": "TSLA",
          "y": 35501508332.0,
          "price": 430.41,
          "change": 3.32,
          "color": "#00C853"
        },
        {
          "x": "AMZN",
          "y": 11135921362.0,
          "price": 239.3,
          "change": -1.01,
          "color": "#F44336"
        },
        {
          "x": "HD",
          "y": 1406810190.0,
          "price": 374.59,
          "change": 0.75,
          "color": "#81C784"
        },
        {
          "x": "SBUX",
          "y": 987938352.0,
          "price": 91.95,
          "change": -2.06,
          "color": "#F44336"
        },
        {
          "x": "MCD",
          "y": 939708000.0,
          "price": 315.0,
          "change": -0.16,
          "color": "#EF9A9A"
        },
        {
          "x": "TJX",
          "y": 901241964.0,
          "price": 149.81,
          "change": 1.59,
          "color": "#4CAF50"
        },
        {
          "x": "NKE",
          "y": 884068450.0,
          "price": 61.81,
          "change": -1.26,
          "color": "#F44336"
        },
        {
          "x": "LOW",
          "y": 854405050.0,
          "price": 267.06,
          "change": 0.16,
          "color": "#81C784"
        }
      ]
    },
    {
      "name": "Comm. Services",
      "data": [
        {
          "x": "META",
          "y": 16982912900.0,
          "price": 716.5,
          "change": -2.95,
          "color": "#F44336"
        },
        {
          "x": "GOOGL",
          "y": 10471409000.0,
          "price": 338.0,
          "change": -0.07,
          "color": "#EF9A9A"
        },
        {
          "x": "VZ",
          "y": 5497966293.0,
          "price": 44.52,
          "change": 11.83,
          "color": "#00C853"
        },
        {
          "x": "NFLX",
          "y": 3814424230.0,
          "price": 83.49,
          "change": 0.4,
          "color": "#81C784"
        },
        {
          "x": "T",
          "y": 2049931206.0,
          "price": 26.21,
          "change": 4.3,
          "color": "#00C853"
        },
        {
          "x": "DIS",
          "y": 2016604615.0,
          "price": 112.8,
          "change": 1.09,
          "color": "#4CAF50"
        },
        {
          "x": "CMCSA",
          "y": 1526097650.0,
          "price": 29.75,
          "change": 1.74,
          "color": "#4CAF50"
        },
        {
          "x": "CHTR",
          "y": 1483301321.0,
          "price": 206.12,
          "change": 7.62,
          "color": "#00C853"
        }
      ]
    },
    {
      "name": "Financials",
      "data": [
        {
          "x": "JPM",
          "y": 3655813921.0,
          "price": 305.89,
          "change": -0.17,
          "color": "#EF9A9A"
        },
        {
          "x": "V",
          "y": 3603305079.0,
          "price": 321.83,
          "change": -3.0,
          "color": "#B71C1C"
        },
        {
          "x": "BRK-B",
          "y": 2439891069.0,
          "price": 480.53,
          "change": 0.78,
          "color": "#81C784"
        },
        {
          "x": "MA",
          "y": 2320514556.0,
          "price": 538.79,
          "change": -0.91,
          "color": "#EF9A9A"
        },
        {
          "x": "BAC",
          "y": 1837751466.0,
          "price": 53.2,
          "change": 0.23,
          "color": "#81C784"
        },
        {
          "x": "GS",
          "y": 1770918161.0,
          "price": 935.41,
          "change": -0.5,
          "color": "#EF9A9A"
        },
        {
          "x": "WFC",
          "y": 1656546097.0,
          "price": 90.49,
          "change": -0.17,
          "color": "#EF9A9A"
        },
        {
          "x": "MS",
          "y": 1358405103.0,
          "price": 182.8,
          "change": 0.77,
          "color": "#81C784"
        }
      ]
    },
    {
      "name": "Healthcare",
      "data": [
        {
          "x": "UNH",
          "y": 3443992009.0,
          "price": 286.93,
          "change": -1.83,
          "color": "#F44336"
        },
        {
          "x": "LLY",
          "y": 3424565666.0,
          "price": 1037.15,
          "change": 1.27,
          "color": "#4CAF50"
        },
        {
          "x": "JNJ",
          "y": 2509908075.0,
          "price": 227.25,
          "change": -0.02,
          "color": "#EF9A9A"
        },
        {
          "x": "TMO",
          "y": 2175978572.0,
          "price": 578.61,
          "change": -2.29,
          "color": "#F44336"
        },
        {
          "x": "MRK",
          "y": 2101602785.0,
          "price": 110.27,
          "change": 1.78,
          "color": "#4CAF50"
        },
        {
          "x": "ABT",
          "y": 1915963473.0,
          "price": 109.3,
          "change": 3.03,
          "color": "#00C853"
        },
        {
          "x": "ABBV",
          "y": 1476816786.0,
          "price": 223.01,
          "change": 1.17,
          "color": "#4CAF50"
        },
        {
          "x": "PFE",
          "y": 1363558420.0,
          "price": 26.44,
          "change": 1.3,
          "color": "#4CAF50"
        }
      ]
    },
    {
      "name": "Consumer Staples",
      "data": [
        {
          "x": "WMT",
          "y": 2645229664.0,
          "price": 119.14,
          "change": 1.47,
          "color": "#4CAF50"
        },
        {
          "x": "COST",
          "y": 2252180825.0,
          "price": 940.25,
          "change": -1.19,
          "color": "#F44336"
        },
        {
          "x": "KO",
          "y": 1975911580.0,
          "price": 74.81,
          "change": 1.88,
          "color": "#4CAF50"
        },
        {
          "x": "PEP",
          "y": 1941622091.0,
          "price": 153.63,
          "change": 3.32,
          "color": "#00C853"
        },
        {
          "x": "PG",
          "y": 1919693253.0,
          "price": 151.77,
          "change": 1.25,
          "color": "#4CAF50"
        },
        {
          "x": "PM",
          "y": 1478442068.0,
          "price": 179.44,
          "change": 0.87,
          "color": "#81C784"
        },
        {
          "x": "CL",
          "y": 1256773610.0,
          "price": 90.29,
          "change": 5.92,
          "color": "#00C853"
        },
        {
          "x": "MO",
          "y": 820933592.0,
          "price": 61.99,
          "change": 3.73,
          "color": "#00C853"
        }
      ]
    },
    {
      "name": "Energy",
      "data": [
        {
          "x": "XOM",
          "y": 4190657479.0,
          "price": 141.4,
          "change": 0.63,
          "color": "#81C784"
        },
        {
          "x": "CVX",
          "y": 4057555160.0,
          "price": 176.9,
          "change": 3.34,
          "color": "#00C853"
        },
        {
          "x": "COP",
          "y": 955570248.0,
          "price": 104.23,
          "change": 1.39,
          "color": "#4CAF50"
        },
        {
          "x": "SLB",
          "y": 793296554.0,
          "price": 48.38,
          "change": -0.14,
          "color": "#EF9A9A"
        },
        {
          "x": "EOG",
          "y": 757740882.0,
          "price": 112.13,
          "change": 0.04,
          "color": "#81C784"
        },
        {
          "x": "VLO",
          "y": 597793683.0,
          "price": 181.43,
          "change": -0.58,
          "color": "#EF9A9A"
        },
        {
          "x": "MPC",
          "y": 369593768.0,
          "price": 176.19,
          "change": 0.26,
          "color": "#81C784"
        },
        {
          "x": "PSX",
          "y": 268428483.0,
          "price": 143.56,
          "change": -0.36,
          "color": "#EF9A9A"
        }
      ]
    },
    {
      "name": "Industrials",
      "data": [
        {
          "x": "GE",
          "y": 2278314640.0,
          "price": 306.79,
          "change": 2.65,
          "color": "#4CAF50"
        },
        {
          "x": "CAT",
          "y": 2167513080.0,
          "price": 657.36,
          "change": -1.18,
          "color": "#F44336"
        },
        {
          "x": "BA",
          "y": 1615168812.0,
          "price": 233.72,
          "change": -0.14,
          "color": "#EF9A9A"
        },
        {
          "x": "HON",
          "y": 1528752413.0,
          "price": 227.52,
          "change": 0.12,
          "color": "#81C784"
        },
        {
          "x": "RTX",
          "y": 1451900034.0,
          "price": 200.93,
          "change": 0.53,
          "color": "#81C784"
        },
        {
          "x": "UNP",
          "y": 903042633.0,
          "price": 235.1,
          "change": 0.65,
          "color": "#81C784"
        },
        {
          "x": "DE",
          "y": 801398400.0,
          "price": 528.0,
          "change": -0.39,
          "color": "#EF9A9A"
        },
        {
          "x": "MMM",
          "y": 725702729.0,
          "price": 153.16,
          "change": -2.06,
          "color": "#F44336"
        }
      ]
    },
    {
      "name": "Materials",
      "data": [
        {
          "x": "FCX",
          "y": 2454312251.0,
          "price": 60.23,
          "change": -7.52,
          "color": "#B71C1C"
        },
        {
          "x": "NEM",
          "y": 2150996896.0,
          "price": 112.35,
          "change": -11.49,
          "color": "#B71C1C"
        },
        {
          "x": "LIN",
          "y": 1286918917.0,
          "price": 456.97,
          "change": 0.43,
          "color": "#81C784"
        },
        {
          "x": "SHW",
          "y": 788081041.0,
          "price": 354.64,
          "change": 0.02,
          "color": "#81C784"
        },
        {
          "x": "APD",
          "y": 700706500.0,
          "price": 272.5,
          "change": 6.44,
          "color": "#00C853"
        },
        {
          "x": "NUE",
          "y": 544622944.0,
          "price": 177.72,
          "change": -1.22,
          "color": "#F44336"
        },
        {
          "x": "DOW",
          "y": 522036671.0,
          "price": 27.55,
          "change": 1.44,
          "color": "#4CAF50"
        },
        {
          "x": "DD",
          "y": 197249104.0,
          "price": 43.92,
          "change": -1.52,
          "color": "#F44336"
        }
      ]
    },
    {
      "name": "Utilities",
      "data": [
        {
          "x": "NEE",
          "y": 896949196.0,
          "price": 87.9,
          "change": -0.32,
          "color": "#EF9A9A"
        },
        {
          "x": "SRE",
          "y": 697063230.0,
          "price": 87.01,
          "change": -0.1,
          "color": "#EF9A9A"
        },
        {
          "x": "DUK",
          "y": 679924041.0,
          "price": 121.35,
          "change": 0.38,
          "color": "#81C784"
        },
        {
          "x": "D",
          "y": 494416875.0,
          "price": 60.17,
          "change": -1.08,
          "color": "#F44336"
        },
        {
          "x": "SO",
          "y": 477344075.0,
          "price": 89.31,
          "change": 0.19,
          "color": "#81C784"
        },
        {
          "x": "AEP",
          "y": 436083042.0,
          "price": 119.78,
          "change": 0.48,
          "color": "#81C784"
        },
        {
          "x": "XEL",
          "y": 298200826.0,
          "price": 76.06,
          "change": 0.12,
          "color": "#81C784"
        },
        {
          "x": "EXC",
          "y": 292798500.0,
          "price": 44.78,
          "change": 0.83,
          "color": "#81C784"
        }
      ]
    },
    {
      "name": "Real Estate",
      "data": [
        {
          "x": "PLD",
          "y": 631375092.0,
          "price": 130.56,
          "change": 0.12,
          "color": "#81C784"
        },
        {
          "x": "AMT",
          "y": 628250900.0,
          "price": 179.28,
          "change": -1.14,
          "color": "#F44336"
        },
        {
          "x": "SPG",
          "y": 577698800.0,
          "price": 191.31,
          "change": 0.8,
          "color": "#81C784"
        },
        {
          "x": "EQIX",
          "y": 533686588.0,
          "price": 820.93,
          "change": -0.62,
          "color": "#EF9A9A"
        },
        {
          "x": "WELL",
          "y": 526447366.0,
          "price": 188.36,
          "change": 1.44,
          "color": "#4CAF50"
        },
        {
          "x": "O",
          "y": 446412955.0,
          "price": 61.16,
          "change": 1.07,
          "color": "#4CAF50"
        },
        {
          "x": "PSA",
          "y": 421742134.0,
          "price": 276.19,
          "change": -0.45,
          "color": "#EF9A9A"
        },
        {
          "x": "CCI",
          "y": 336779386.0,
          "price": 86.81,
          "change": -0.13,
          "color": "#EF9A9A"
        }
      ]
    }
  ]
}