{
  "last_updated": "2026-04-17T10:23:33.181276",
  "smart_money": {
    "total_recommendations": 120,
    "active": 48,
    "successful": 39,
    "failed": 33,
    "hit_rate": 54.2,
    "avg_return": 1.26,
    "best_pick": {
      "ticker": "HAL",
      "return_pct": 28.89
    },
    "worst_pick": {
      "ticker": "CTSH",
      "return_pct": -28.57
    },
    "history": [
      {
        "ticker": "WDC",
        "name": "Western Digital Corporation",
        "recommended_date": "2026-04-10",
        "recommended_price": 311.96,
        "target_price": 0,
        "current_price": 361.69,
        "days_held": 7,
        "return_pct": 15.94,
        "target_hit": false,
        "status": "success"
      },
      {
        "ticker": "SBAC",
        "name": "SBA Communications Corporation",
        "recommended_date": "2026-04-10",
        "recommended_price": 205.86,
        "target_price": 0,
        "current_price": 221.76,
        "days_held": 7,
        "return_pct": 7.72,
        "target_hit": false,
        "status": "active"
      },
      {
        "ticker": "CTRA",
        "name": "Coterra Energy Inc.",
        "recommended_date": "2026-04-10",
        "recommended_price": 34.91,
        "target_price": 0,
        "current_price": 31.97,
        "days_held": 7,
        "return_pct": -8.42,
        "target_hit": false,
        "status": "active"
      },
      {
        "ticker": "WDC",
        "name": "Western Digital Corporation",
        "recommended_date": "2026-04-09",
        "recommended_price": 311.96,
        "target_price": 0,
        "current_price": 361.69,
        "days_held": 8,
        "return_pct": 15.94,
        "target_hit": false,
        "status": "success"
      },
      {
        "ticker": "SBAC",
        "name": "SBA Communications Corporation",
        "recommended_date": "2026-04-09",
        "recommended_price": 205.86,
        "target_price": 0,
        "current_price": 221.76,
        "days_held": 8,
        "return_pct": 7.72,
        "target_hit": false,
        "status": "active"
      },
      {
        "ticker": "CTRA",
        "name": "Coterra Energy Inc.",
        "recommended_date": "2026-04-09",
        "recommended_price": 34.91,
        "target_price": 0,
        "current_price": 31.97,
        "days_held": 8,
        "return_pct": -8.42,
        "target_hit": false,
        "status": "active"
      },
      {
        "ticker": "ELV",
        "name": "Elevance Health, Inc.",
        "recommended_date": "2026-04-09",
        "recommended_price": 311.83,
        "target_price": 0,
        "current_price": 315.82,
        "days_held": 8,
        "return_pct": 1.28,
        "target_hit": false,
        "status": "active"
      },
      {
        "ticker": "TER",
        "name": "Teradyne, Inc.",
        "recommended_date": "2026-04-09",
        "recommended_price": 320.48,
        "target_price": 0,
        "current_price": 365.92,
        "days_held": 8,
        "return_pct": 14.18,
        "target_hit": false,
        "status": "success"
      },
      {
        "ticker": "VRSN",
        "name": "VeriSign, Inc.",
        "recommended_date": "2026-04-09",
        "recommended_price": 274.75,
        "target_price": 0,
        "current_price": 273.85,
        "days_held": 8,
        "return_pct": -0.33,
        "target_hit": false,
        "status": "active"
      },
      {
        "ticker": "DVN",
        "name": "Devon Energy Corporation",
        "recommended_date": "2026-04-09",
        "recommended_price": 49.95,
        "target_price": 0,
        "current_price": 45.78,
        "days_held": 8,
        "return_pct": -8.35,
        "target_hit": false,
        "status": "active"
      },
      {
        "ticker": "XOM",
        "name": "Exxon Mobil Corporation",
        "recommended_date": "2026-04-09",
        "recommended_price": 163.91,
        "target_price": 0,
        "current_price": 151.98,
        "days_held": 8,
        "return_pct": -7.28,
        "target_hit": false,
        "status": "active"
      },
      {
        "ticker": "CE",
        "name": "Celanese Corporation",
        "recommended_date": "2026-04-09",
        "recommended_price": 63.57,
        "target_price": 0,
        "current_price": 68.34,
        "days_held": 8,
        "return_pct": 7.5,
        "target_hit": false,
        "status": "active"
      },
      {
        "ticker": "ROST",
        "name": "Ross Stores, Inc.",
        "recommended_date": "2026-04-09",
        "recommended_price": 216.34,
        "target_price": 0,
        "current_price": 221.97,
        "days_held": 8,
        "return_pct": 2.6,
        "target_hit": false,
        "status": "active"
      },
      {
        "ticker": "WDC",
        "name": "Western Digital Corporation",
        "recommended_date": "2026-04-08",
        "recommended_price": 311.96,
        "target_price": 0,
        "current_price": 361.69,
        "days_held": 9,
        "return_pct": 15.94,
        "target_hit": false,
        "status": "success"
      },
      {
        "ticker": "SBAC",
        "name": "SBA Communications Corporation",
        "recommended_date": "2026-04-08",
        "recommended_price": 205.86,
        "target_price": 0,
        "current_price": 221.76,
        "days_held": 9,
        "return_pct": 7.72,
        "target_hit": false,
        "status": "active"
      },
      {
        "ticker": "CTRA",
        "name": "Coterra Energy Inc.",
        "recommended_date": "2026-04-08",
        "recommended_price": 34.91,
        "target_price": 0,
        "current_price": 31.97,
        "days_held": 9,
        "return_pct": -8.42,
        "target_hit": false,
        "status": "active"
      },
      {
        "ticker": "ELV",
        "name": "Elevance Health, Inc.",
        "recommended_date": "2026-04-08",
        "recommended_price": 311.83,
        "target_price": 0,
        "current_price": 315.82,
        "days_held": 9,
        "return_pct": 1.28,
        "target_hit": false,
        "status": "active"
      },
      {
        "ticker": "TER",
        "name": "Teradyne, Inc.",
        "recommended_date": "2026-04-08",
        "recommended_price": 320.48,
        "target_price": 0,
        "current_price": 365.92,
        "days_held": 9,
        "return_pct": 14.18,
        "target_hit": false,
        "status": "success"
      },
      {
        "ticker": "VRSN",
        "name": "VeriSign, Inc.",
        "recommended_date": "2026-04-08",
        "recommended_price": 274.75,
        "target_price": 0,
        "current_price": 273.85,
        "days_held": 9,
        "return_pct": -0.33,
        "target_hit": false,
        "status": "active"
      },
      {
        "ticker": "DVN",
        "name": "Devon Energy Corporation",
        "recommended_date": "2026-04-08",
        "recommended_price": 49.95,
        "target_price": 0,
        "current_price": 45.78,
        "days_held": 9,
        "return_pct": -8.35,
        "target_hit": false,
        "status": "active"
      },
      {
        "ticker": "XOM",
        "name": "Exxon Mobil Corporation",
        "recommended_date": "2026-04-08",
        "recommended_price": 163.91,
        "target_price": 0,
        "current_price": 151.98,
        "days_held": 9,
        "return_pct": -7.28,
        "target_hit": false,
        "status": "active"
      },
      {
        "ticker": "CE",
        "name": "Celanese Corporation",
        "recommended_date": "2026-04-08",
        "recommended_price": 63.57,
        "target_price": 0,
        "current_price": 68.34,
        "days_held": 9,
        "return_pct": 7.5,
        "target_hit": false,
        "status": "active"
      },
      {
        "ticker": "ROST",
        "name": "Ross Stores, Inc.",
        "recommended_date": "2026-04-08",
        "recommended_price": 216.34,
        "target_price": 0,
        "current_price": 221.97,
        "days_held": 9,
        "return_pct": 2.6,
        "target_hit": false,
        "status": "active"
      },
      {
        "ticker": "ROST",
        "name": "Ross Stores, Inc.",
        "recommended_date": "2026-04-07",
        "recommended_price": 219.98,
        "target_price": 0,
        "current_price": 221.97,
        "days_held": 10,
        "return_pct": 0.9,
        "target_hit": false,
        "status": "active"
      },
      {
        "ticker": "WDC",
        "name": "Western Digital Corporation",
        "recommended_date": "2026-04-07",
        "recommended_price": 294.97,
        "target_price": 0,
        "current_price": 361.69,
        "days_held": 10,
        "return_pct": 22.62,
        "target_hit": false,
        "status": "success"
      },
      {
        "ticker": "LNT",
        "name": "Alliant Energy Corporation",
        "recommended_date": "2026-04-07",
        "recommended_price": 72.85,
        "target_price": 0,
        "current_price": 72.77,
        "days_held": 10,
        "return_pct": -0.11,
        "target_hit": false,
        "status": "active"
      },
      {
        "ticker": "SLB",
        "name": "SLB N.V.",
        "recommended_date": "2026-04-07",
        "recommended_price": 49.44,
        "target_price": 0,
        "current_price": 51.73,
        "days_held": 10,
        "return_pct": 4.63,
        "target_hit": false,
        "status": "active"
      },
      {
        "ticker": "CMS",
        "name": "CMS Energy Corporation",
        "recommended_date": "2026-04-07",
        "recommended_price": 78.58,
        "target_price": 0,
        "current_price": 78.11,
        "days_held": 10,
        "return_pct": -0.6,
        "target_hit": false,
        "status": "active"
      },
      {
        "ticker": "DVN",
        "name": "Devon Energy Corporation",
        "recommended_date": "2026-04-07",
        "recommended_price": 49.49,
        "target_price": 0,
        "current_price": 45.78,
        "days_held": 10,
        "return_pct": -7.5,
        "target_hit": false,
        "status": "active"
      },
      {
        "ticker": "NEE",
        "name": "NextEra Energy, Inc.",
        "recommended_date": "2026-04-07",
        "recommended_price": 93.15,
        "target_price": 0,
        "current_price": 91.83,
        "days_held": 10,
        "return_pct": -1.42,
        "target_hit": false,
        "status": "active"
      },
      {
        "ticker": "AKAM",
        "name": "Akamai Technologies, Inc.",
        "recommended_date": "2026-04-07",
        "recommended_price": 118.0,
        "target_price": 0,
        "current_price": 96.81,
        "days_held": 10,
        "return_pct": -17.96,
        "target_hit": false,
        "status": "failed"
      },
      {
        "ticker": "NFLX",
        "name": "Netflix, Inc.",
        "recommended_date": "2026-04-07",
        "recommended_price": 98.66,
        "target_price": 0,
        "current_price": 107.79,
        "days_held": 10,
        "return_pct": 9.25,
        "target_hit": false,
        "status": "active"
      },
      {
        "ticker": "LIN",
        "name": "Linde plc",
        "recommended_date": "2026-04-07",
        "recommended_price": 502.6,
        "target_price": 0,
        "current_price": 499.22,
        "days_held": 10,
        "return_pct": -0.67,
        "target_hit": false,
        "status": "active"
      },
      {
        "ticker": "ROST",
        "name": "Ross Stores, Inc.",
        "recommended_date": "2026-04-06",
        "recommended_price": 219.98,
        "target_price": 0,
        "current_price": 221.97,
        "days_held": 11,
        "return_pct": 0.9,
        "target_hit": false,
        "status": "active"
      },
      {
        "ticker": "WDC",
        "name": "Western Digital Corporation",
        "recommended_date": "2026-04-06",
        "recommended_price": 294.97,
        "target_price": 0,
        "current_price": 361.69,
        "days_held": 11,
        "return_pct": 22.62,
        "target_hit": false,
        "status": "success"
      },
      {
        "ticker": "LNT",
        "name": "Alliant Energy Corporation",
        "recommended_date": "2026-04-06",
        "recommended_price": 72.85,
        "target_price": 0,
        "current_price": 72.77,
        "days_held": 11,
        "return_pct": -0.11,
        "target_hit": false,
        "status": "active"
      },
      {
        "ticker": "SLB",
        "name": "SLB N.V.",
        "recommended_date": "2026-04-06",
        "recommended_price": 49.44,
        "target_price": 0,
        "current_price": 51.73,
        "days_held": 11,
        "return_pct": 4.63,
        "target_hit": false,
        "status": "active"
      },
      {
        "ticker": "CMS",
        "name": "CMS Energy Corporation",
        "recommended_date": "2026-04-06",
        "recommended_price": 78.58,
        "target_price": 0,
        "current_price": 78.11,
        "days_held": 11,
        "return_pct": -0.6,
        "target_hit": false,
        "status": "active"
      },
      {
        "ticker": "DVN",
        "name": "Devon Energy Corporation",
        "recommended_date": "2026-04-06",
        "recommended_price": 49.49,
        "target_price": 0,
        "current_price": 45.78,
        "days_held": 11,
        "return_pct": -7.5,
        "target_hit": false,
        "status": "active"
      },
      {
        "ticker": "NEE",
        "name": "NextEra Energy, Inc.",
        "recommended_date": "2026-04-06",
        "recommended_price": 93.15,
        "target_price": 0,
        "current_price": 91.83,
        "days_held": 11,
        "return_pct": -1.42,
        "target_hit": false,
        "status": "active"
      },
      {
        "ticker": "AKAM",
        "name": "Akamai Technologies, Inc.",
        "recommended_date": "2026-04-06",
        "recommended_price": 118.0,
        "target_price": 0,
        "current_price": 96.81,
        "days_held": 11,
        "return_pct": -17.96,
        "target_hit": false,
        "status": "failed"
      },
      {
        "ticker": "NFLX",
        "name": "Netflix, Inc.",
        "recommended_date": "2026-04-06",
        "recommended_price": 98.66,
        "target_price": 0,
        "current_price": 107.79,
        "days_held": 11,
        "return_pct": 9.25,
        "target_hit": false,
        "status": "active"
      },
      {
        "ticker": "LIN",
        "name": "Linde plc",
        "recommended_date": "2026-04-06",
        "recommended_price": 502.6,
        "target_price": 0,
        "current_price": 499.22,
        "days_held": 11,
        "return_pct": -0.67,
        "target_hit": false,
        "status": "active"
      },
      {
        "ticker": "ROST",
        "name": "Ross Stores, Inc.",
        "recommended_date": "2026-04-05",
        "recommended_price": 219.98,
        "target_price": 0,
        "current_price": 221.97,
        "days_held": 12,
        "return_pct": 0.9,
        "target_hit": false,
        "status": "active"
      },
      {
        "ticker": "WDC",
        "name": "Western Digital Corporation",
        "recommended_date": "2026-04-05",
        "recommended_price": 294.97,
        "target_price": 0,
        "current_price": 361.69,
        "days_held": 12,
        "return_pct": 22.62,
        "target_hit": false,
        "status": "success"
      },
      {
        "ticker": "LNT",
        "name": "Alliant Energy Corporation",
        "recommended_date": "2026-04-05",
        "recommended_price": 72.85,
        "target_price": 0,
        "current_price": 72.77,
        "days_held": 12,
        "return_pct": -0.11,
        "target_hit": false,
        "status": "active"
      },
      {
        "ticker": "SLB",
        "name": "SLB N.V.",
        "recommended_date": "2026-04-05",
        "recommended_price": 49.44,
        "target_price": 0,
        "current_price": 51.73,
        "days_held": 12,
        "return_pct": 4.63,
        "target_hit": false,
        "status": "active"
      },
      {
        "ticker": "CMS",
        "name": "CMS Energy Corporation",
        "recommended_date": "2026-04-05",
        "recommended_price": 78.58,
        "target_price": 0,
        "current_price": 78.11,
        "days_held": 12,
        "return_pct": -0.6,
        "target_hit": false,
        "status": "active"
      },
      {
        "ticker": "DVN",
        "name": "Devon Energy Corporation",
        "recommended_date": "2026-04-05",
        "recommended_price": 49.49,
        "target_price": 0,
        "current_price": 45.78,
        "days_held": 12,
        "return_pct": -7.5,
        "target_hit": false,
        "status": "active"
      },
      {
        "ticker": "NEE",
        "name": "NextEra Energy, Inc.",
        "recommended_date": "2026-04-05",
        "recommended_price": 93.15,
        "target_price": 0,
        "current_price": 91.83,
        "days_held": 12,
        "return_pct": -1.42,
        "target_hit": false,
        "status": "active"
      }
    ]
  },
  "closing_bell": {
    "total_recommendations": 0,
    "active": 0,
    "successful": 0,
    "failed": 0,
    "hit_rate": 0.0,
    "avg_return": 0.0,
    "best_pick": {
      "ticker": "",
      "return_pct": 0.0
    },
    "worst_pick": {
      "ticker": "",
      "return_pct": 0.0
    },
    "history": []
  }
}